diverge/__init__.py
diverge/_asymcpp.cp310-win_amd64.pyd
diverge/_effectivecpp.cp310-win_amd64.pyd
diverge/_fdrcpp.cp310-win_amd64.pyd
diverge/_gu2001cpp.cp310-win_amd64.pyd
diverge/_gu99cpp.cp310-win_amd64.pyd
diverge/_rvscpp.cp310-win_amd64.pyd
diverge/_type2cpp.cp310-win_amd64.pyd
diverge/_typeOneAnalysiscpp.cp310-win_amd64.pyd
diverge/binding.py
diverge/super_cluster.py
diverge/treeplot.py
diverge/utils.py
diverge-4.0.4.dist-info/LICENSE
diverge-4.0.4.dist-info/METADATA
diverge-4.0.4.dist-info/WHEEL
diverge-4.0.4.dist-info/top_level.txt
diverge-4.0.4.dist-info/RECORD
